Metadata-Version: 1.0
Name: distributions-kiransk
Version: 0.1
Summary: Gaussian and Binomial distributions
Home-page: UNKNOWN
Author: Sai Kiran Tanikella
Author-email: saikirantanikella@gmail.com
License: UNKNOWN
Platform: UNKNOWN
